{
  "project_info": {
    "project_number": "818208259263",
    "firebase_url": "https://colorsmash-708a9.firebaseio.com",
    "project_id": "colorsmash-708a9",
    "storage_bucket": "colorsmash-708a9.appspot.com"
  },
  "client": [
    {
      "client_info": {
        "mobilesdk_app_id": "1:818208259263:android:aff04f369a8bf776",
        "android_client_info": {
          "package_name": "com.example.colorsmash"
        }
      },
      "oauth_client": [
        {
          "client_id": "818208259263-jsmtooa926htfar7memnq91bmpu68ac7.apps.googleusercontent.com",
          "client_type": 1,
          "android_info": {
            "package_name": "com.example.colorsmash",
            "certificate_hash": "b9cc6df7c2f3090c92e478279cc1a77688e54420"
          }
        }
      ],
      "api_key": [
        {
          "current_key": "AIzaSyDFSuAoYLYdyEh-IylRD6LldYBFPfc9gxU"
        }
      ],
      "services": {
        "appinvite_service": {
          "other_platform_oauth_client": [
            {
              "client_id": "818208259263-t21s3l7sq3q242fv53i85ccdlbc57fpq.apps.googleusercontent.com",
              "client_type": 3
            }
          ]
        }
      }
    }
  ],
  "configuration_version": "1"
}